{"cameraMode":{"drawMode":0,"name":"Shaded","section":"Shading Mode"},"sceneLighting":true,"audioPlay":false,"sceneViewState":{"m_AlwaysRefresh":false,"showFog":true,"showSkybox":true,"showFlares":true,"showImageEffects":true,"showParticleSystems":true,"showVisualEffectGraphs":true,"m_FxEnabled":true},"in2DMode":false,"pivot":{"x":839.6998291015625,"y":482.0548095703125,"z":-495.6443176269531},"rotation":{"x":-0.0764455646276474,"y":-0.15000663697719575,"z":0.010745372623205185,"w":-0.9877740740776062},"size":103.07764434814453,"orthographic":false}